setup.cfg
setup.py
dmpling/__init__.py
dmpling/cs.py
dmpling/dmp.py
dmpling/utils.py
dmpling.egg-info/PKG-INFO
dmpling.egg-info/SOURCES.txt
dmpling.egg-info/dependency_links.txt
dmpling.egg-info/not-zip-safe
dmpling.egg-info/requires.txt
dmpling.egg-info/top_level.txt