Metadata-Version: 1.1
Name: dmpling
Version: 0.0.1
Summary: Dynamic Movement Primitives in Python
Home-page: https://github.com/tsitsimis/dmpling
Author: Theodore Tsitsimis
Author-email: th.tsitsimis@gmail.com
License: MIT
Download-URL: https://github.com/tsitsimis/dmpling/archive/0.0.1.tar.gz
Keywords: robotics,motion planning,imitation learning
Platform: UNKNOWN
